NiukeSuanfaGongchengshiQiuzhiJingyanFenxiangJiqiXuexiFangxiang20212022Fix1/README.md
NiukeSuanfaGongchengshiQiuzhiJingyanFenxiangJiqiXuexiFangxiang20212022Fix1/__init__.py
NiukeSuanfaGongchengshiQiuzhiJingyanFenxiangJiqiXuexiFangxiang20212022Fix1/__main__.py
NiukeSuanfaGongchengshiQiuzhiJingyanFenxiangJiqiXuexiFangxiang20212022Fix1/file.epub
NiukeSuanfaGongchengshiQiuzhiJingyanFenxiangJiqiXuexiFangxiang20212022Fix1/index.html
NiukeSuanfaGongchengshiQiuzhiJingyanFenxiangJiqiXuexiFangxiang20212022Fix1/css/__init__.py
NiukeSuanfaGongchengshiQiuzhiJingyanFenxiangJiqiXuexiFangxiang20212022Fix1/css/annotations.css
NiukeSuanfaGongchengshiQiuzhiJingyanFenxiangJiqiXuexiFangxiang20212022Fix1/css/main.css
NiukeSuanfaGongchengshiQiuzhiJingyanFenxiangJiqiXuexiFangxiang20212022Fix1/css/normalize.css
NiukeSuanfaGongchengshiQiuzhiJingyanFenxiangJiqiXuexiFangxiang20212022Fix1/css/popup.css
NiukeSuanfaGongchengshiQiuzhiJingyanFenxiangJiqiXuexiFangxiang20212022Fix1/font/__init__.py
NiukeSuanfaGongchengshiQiuzhiJingyanFenxiangJiqiXuexiFangxiang20212022Fix1/font/fontello.eot
NiukeSuanfaGongchengshiQiuzhiJingyanFenxiangJiqiXuexiFangxiang20212022Fix1/font/fontello.svg
NiukeSuanfaGongchengshiQiuzhiJingyanFenxiangJiqiXuexiFangxiang20212022Fix1/font/fontello.ttf
NiukeSuanfaGongchengshiQiuzhiJingyanFenxiangJiqiXuexiFangxiang20212022Fix1/font/fontello.woff
NiukeSuanfaGongchengshiQiuzhiJingyanFenxiangJiqiXuexiFangxiang20212022Fix1/img/__init__.py
NiukeSuanfaGongchengshiQiuzhiJingyanFenxiangJiqiXuexiFangxiang20212022Fix1/img/annotator-glyph-sprite.png
NiukeSuanfaGongchengshiQiuzhiJingyanFenxiangJiqiXuexiFangxiang20212022Fix1/img/annotator-icon-sprite.png
NiukeSuanfaGongchengshiQiuzhiJingyanFenxiangJiqiXuexiFangxiang20212022Fix1/img/apple-touch-icon.png
NiukeSuanfaGongchengshiQiuzhiJingyanFenxiangJiqiXuexiFangxiang20212022Fix1/img/cancelfullscreen.png
NiukeSuanfaGongchengshiQiuzhiJingyanFenxiangJiqiXuexiFangxiang20212022Fix1/img/close.png
niuke_suanfa_gongchengshi_qiuzhi_jingyan_fenxiang_jiqi_xuexi_fangxiang_2021_2022_fix1-2025.3.25.1.dist-info/METADATA
niuke_suanfa_gongchengshi_qiuzhi_jingyan_fenxiang_jiqi_xuexi_fangxiang_2021_2022_fix1-2025.3.25.1.dist-info/WHEEL
niuke_suanfa_gongchengshi_qiuzhi_jingyan_fenxiang_jiqi_xuexi_fangxiang_2021_2022_fix1-2025.3.25.1.dist-info/entry_points.txt
niuke_suanfa_gongchengshi_qiuzhi_jingyan_fenxiang_jiqi_xuexi_fangxiang_2021_2022_fix1-2025.3.25.1.dist-info/top_level.txt
niuke_suanfa_gongchengshi_qiuzhi_jingyan_fenxiang_jiqi_xuexi_fangxiang_2021_2022_fix1-2025.3.25.1.dist-info/RECORD
